Metadata-Version: 1.0
Name: jx-distributions
Version: 2.1.0
Summary: This code in this package uses the concept of Object-Oriented Programming to      carry out some simple calculations related to Gaussian and Bionomial distributions.      This is a course project from the Udacity Data Scientist Nanodegree program. 
Home-page: UNKNOWN
Author: Jing Xie
Author-email: jing.xie@usask.ca
License: UNKNOWN
Platform: UNKNOWN
